[
  {
    "params": {
      "home_team": "挪威",
      "away_team": "英格兰",
      "home_odds": 3.55,
      "away_odds": 1.98,
      "stake": 50,
      "strategy": "B"
    },
    "report": "## 🎯 Match: 挪威 vs 英格兰\n---\n### 🎗️ 核心预测 (p_final 贝叶斯融合)\n- **主胜概率**: 30.0% [███░░░░░░░]\n- **平局概率**: 24.8% [██░░░░░░░░]\n- **客胜概率**: 45.2% [█████░░░░░]\n- **首选推荐**: `客胜`\n- **推荐比分**: `1-1` / `1-2`\n- **总进球数**: `2-3` 球 (期望值: `3.11`)\n\n---\n### 🏅 模型独立输出对照\n*   **Elo 概率**: 主胜 23% | 平 25% | 客 52%\n*   **xG 期望**: 主队 1.45 / 客队 1.66 (基础期望)\n*   **Dixon-Coles 修正**: τ 值为 -0.120 (平局相关性参数)\n*   **Monte Carlo 模拟**: 中位数比分 `1-1`，95% 置信区间主队 `[0-4]` / 客队 `[0-5]`\n\n---\n### 📊 盘口校准输入\n*   📉 **大小球校准**: 盘口 2.75, 大球公平概率 51.0%\n*   ⚖️ **让球校准**: 主队盘口 -0.50, 主队赢盘公平概率 49.5%\n\n---\n### 🏆 精准比分概率 TOP 5\n0. **`1-1`** --- 12.0% [█░░░░░░░░░]\n1. **`1-2`** --- 8.9% [█░░░░░░░░░]\n2. **`2-1`** --- 7.8% [█░░░░░░░░░]\n3. **`2-2`** --- 6.5% [█░░░░░░░░░]\n4. **`0-2`** --- 6.2% [█░░░░░░░░░]\n\n---\n### 🎲 进球数及双建概率\n- **0-1 球**: 17.1% [██░░░░░░░░]\n- **2-3 球**: 45.2% [█████░░░░░]\n- **4+ 球**: 37.7% [████░░░░░░]\n- **双方建功 (BTTS)**: 是 63.2% [██████░░░░] | 否 36.8% [████░░░░░░]\n\n---\n### 🛡️ 风险对冲与冷防建议\n- **冷门期望不败率** (主胜或平局 (挪威不败)): 54.8% [█████░░░░░]\n- **首选冷防比分**: `1-1` (胜率: 12.0%)\n- **三大赛果首选比分分布**: \n  *   🏠 主胜首选: `2-1` (7.8%)\n  *   🤝 平局首选: `1-1` (12.0%)\n  *   🚀 客胜首选: `1-2` (8.9%)\n- **市场投资期望值 (EV)**: `主胜: +6.4%, 平局: -8.1%, 客胜: -10.5%`\n- **最佳期望值推荐 (Value Bet)**: 偏向 `主胜` (EV值为 6.4%, 具备正向投注价值)\n\n---\n### 💰 智能资金分配与对冲投注单 (预算: 50 元)\n### 🔴 策略 A: 等收益分投 (首筑基, 平滑波动)\n- 比分 `1-1` (估算 7.07) — 投 `14.5` 元 (中返 102.8 元)\n- 比分 `1-2` (估算 9.52) — 投 `10.8` 元 (中返 102.8 元)\n- 比分 `2-1` (估算 10.96) — 投 `9.4` 元 (中返 102.8 元)\n- 比分 `2-2` (估算 13.17) — 投 `7.8` 元 (中返 102.8 元)\n- 比分 `0-2` (估算 13.75) — 投 `7.5` 元 (中返 102.8 元)\n👑 **策略 A 净期望利润**: `+52.8` 元 (固定净回报率: `+105.6`%)\n### 🔵 策略 B: 保本主攻分投 (中后期爆发, 主攻暴利)\n- 💛 **保本对冲** `1-1` (估算 7.07) — 投 `7.1` 元 (中返 `50` 元, 保本不赔)\n- 🚀 **主攻比分** `1-2` (估算 9.52) — 投 `13.1` 元 (中返 `124.5` 元, 净赚 `+74.5` 元)\n- 🚀 **主攻比分** `2-1` (估算 10.96) — 投 `11.4` 元 (中返 `124.5` 元, 净赚 `+74.5` 元)\n- 🚀 **主攻比分** `2-2` (估算 13.17) — 投 `9.4` 元 (中返 `124.4` 元, 净赚 `+74.4` 元)\n- 🚀 **主攻比分** `0-2` (估算 13.75) — 投 `9.0` 元 (中返 `124.4` 元, 净赚 `+74.4` 元)\n💪 **策略 B 综述**: 重仓主打胜局高回报, 一旦爆冷打出平局首选比分, 退还全部本金, 本场无风险。\n\n✅ 已确认【策略 B (保本主攻) 】！正在为您生成手机投注单凭证...\n\n📜 【策略 B 投注凭证 — 激进爆发单】\n---------------------------------------------\n赛事: 挪威 vs 英格兰\n总本金: 50.0 元\n投向分拨明细: \n - 💛 【保本对冲防御】比分 `1-1` (赔率 7.80) — 投 `6.4` 元 (若中返 50.0 元)\n - 🚀 【核心主攻进攻】**比分 `1-2` (赔率 8.20) — 投 `13.3` 元 (中返 `108.9` 元, 净赚 `+58.9` 元)\n - 🚀 【核心主攻进攻】**比分 `2-1` (赔率 11.30) — 投 `11.5` 元 (中返 `130.3` 元, 净赚 `+80.3` 元)\n - 🚀 【核心主攻进攻】**比分 `2-2` (赔率 13.50) — 投 `9.6` 元 (中返 `129.5` 元, 净赚 `+79.5` 元)\n - 🚀 【核心主攻进攻】**比分 `0-2` (赔率 10.50) — 投 `9.2` 元 (中返 `96.5` 元, 净赚 `+46.5` 元)\n---------------------------------------------\n💡 凭证已生成。本场若爆冷打出平局首选，将退还 100% 本金，祝您顺利斩获主攻暴利！\n",
    "timestamp": "2026-07-11 11:00:34"
  },
  {
    "params": {
      "home_team": "挪威",
      "away_team": "英格兰",
      "home_odds": 3.55,
      "away_odds": 1.98,
      "stake": 100,
      "strategy": "B"
    },
    "report": "## 🎯 Match: 挪威 vs 英格兰\n---\n### 🎗️ 核心预测 (p_final 贝叶斯融合)\n- **主胜概率**: 29.9% [███░░░░░░░]\n- **平局概率**: 24.9% [██░░░░░░░░]\n- **客胜概率**: 45.2% [█████░░░░░]\n- **首选推荐**: `客胜`\n- **推荐比分**: `1-1` / `1-2`\n- **总进球数**: `2-3` 球 (期望值: `3.11`)\n\n---\n### 🏅 模型独立输出对照\n*   **Elo 概率**: 主胜 23% | 平 25% | 客 52%\n*   **xG 期望**: 主队 1.45 / 客队 1.66 (基础期望)\n*   **Dixon-Coles 修正**: τ 值为 -0.120 (平局相关性参数)\n*   **Monte Carlo 模拟**: 中位数比分 `1-1`，95% 置信区间主队 `[0-4]` / 客队 `[0-5]`\n\n---\n### 📊 盘口校准输入\n*   📉 **大小球校准**: 盘口 2.75, 大球公平概率 51.0%\n*   ⚖️ **让球校准**: 主队盘口 -0.50, 主队赢盘公平概率 49.5%\n\n---\n### 🏆 精准比分概率 TOP 5\n0. **`1-1`** --- 12.0% [█░░░░░░░░░]\n1. **`1-2`** --- 8.9% [█░░░░░░░░░]\n2. **`2-1`** --- 7.8% [█░░░░░░░░░]\n3. **`2-2`** --- 6.5% [█░░░░░░░░░]\n4. **`0-2`** --- 6.2% [█░░░░░░░░░]\n\n---\n### 🎲 进球数及双建概率\n- **0-1 球**: 17.1% [██░░░░░░░░]\n- **2-3 球**: 45.2% [█████░░░░░]\n- **4+ 球**: 37.7% [████░░░░░░]\n- **双方建功 (BTTS)**: 是 63.2% [██████░░░░] | 否 36.8% [████░░░░░░]\n\n---\n### 🛡️ 风险对冲与冷防建议\n- **冷门期望不败率** (主胜或平局 (挪威不败)): 54.8% [█████░░░░░]\n- **首选冷防比分**: `1-1` (胜率: 12.0%)\n- **三大赛果首选比分分布**: \n  *   🏠 主胜首选: `2-1` (7.8%)\n  *   🤝 平局首选: `1-1` (12.0%)\n  *   🚀 客胜首选: `1-2` (8.9%)\n- **市场投资期望值 (EV)**: `主胜: +6.1%, 平局: -7.9%, 客胜: -10.4%`\n- **最佳期望值推荐 (Value Bet)**: 偏向 `主胜` (EV值为 6.1%, 具备正向投注价值)\n\n---\n### 💰 智能资金分配与对冲投注单 (预算: 100 元)\n### 🔴 策略 A: 等收益分投 (首筑基, 平滑波动)\n- 比分 `1-1` (估算 7.07) — 投 `29.1` 元 (中返 205.6 元)\n- 比分 `1-2` (估算 9.52) — 投 `21.6` 元 (中返 205.6 元)\n- 比分 `2-1` (估算 10.96) — 投 `18.8` 元 (中返 205.6 元)\n- 比分 `2-2` (估算 13.17) — 投 `15.6` 元 (中返 205.6 元)\n- 比分 `0-2` (估算 13.75) — 投 `15.0` 元 (中返 205.6 元)\n👑 **策略 A 净期望利润**: `+105.6` 元 (固定净回报率: `+105.6`%)\n### 🔵 策略 B: 保本主攻分投 (中后期爆发, 主攻暴利)\n- 💛 **保本对冲** `1-1` (估算 7.07) — 投 `14.1` 元 (中返 `100` 元, 保本不赔)\n- 🚀 **主攻比分** `1-2` (估算 9.52) — 投 `26.2` 元 (中返 `249.0` 元, 净赚 `+149.0` 元)\n- 🚀 **主攻比分** `2-1` (估算 10.96) — 投 `22.7` 元 (中返 `248.9` 元, 净赚 `+148.9` 元)\n- 🚀 **主攻比分** `2-2` (估算 13.17) — 投 `18.9` 元 (中返 `248.9` 元, 净赚 `+148.9` 元)\n- 🚀 **主攻比分** `0-2` (估算 13.75) — 投 `18.1` 元 (中返 `248.8` 元, 净赚 `+148.8` 元)\n💪 **策略 B 综述**: 重仓主打胜局高回报, 一旦爆冷打出平局首选比分, 退还全部本金, 本场无风险。\n\n✅ 已确认【策略 B (保本主攻) 】！正在为您生成手机投注单凭证...\n\n📜 【策略 B 投注凭证 — 激进爆发单】\n---------------------------------------------\n赛事: 挪威 vs 英格兰\n总本金: 100.0 元\n投向分拨明细: \n - 💛 【保本对冲防御】比分 `1-1` (赔率 7.80) — 投 `12.8` 元 (若中返 100.0 元)\n - 🚀 【核心主攻进攻】**比分 `1-2` (赔率 8.20) — 投 `26.6` 元 (中返 `217.7` 元, 净赚 `+117.7` 元)\n - 🚀 【核心主攻进攻】**比分 `2-1` (赔率 11.30) — 投 `23.1` 元 (中返 `260.6` 元, 净赚 `+160.6` 元)\n - 🚀 【核心主攻进攻】**比分 `2-2` (赔率 13.50) — 投 `19.2` 元 (中返 `259.1` 元, 净赚 `+159.1` 元)\n - 🚀 【核心主攻进攻】**比分 `0-2` (赔率 10.50) — 投 `18.4` 元 (中返 `192.9` 元, 净赚 `+92.9` 元)\n---------------------------------------------\n💡 凭证已生成。本场若爆冷打出平局首选，将退还 100% 本金，祝您顺利斩获主攻暴利！\n",
    "timestamp": "2026-07-11 11:00:04"
  },
  {
    "params": {
      "home_team": "挪威",
      "away_team": "英格兰",
      "home_odds": 3.55,
      "away_odds": 1.98
    },
    "report": "## 🎯 Match: 挪威 vs 英格兰\n---\n### 🎗️ 核心预测 (p_final 贝叶斯融合)\n- **主胜概率**: 29.9% [███░░░░░░░]\n- **平局概率**: 24.9% [██░░░░░░░░]\n- **客胜概率**: 45.1% [█████░░░░░]\n- **首选推荐**: `客胜`\n- **推荐比分**: `1-1` / `1-2`\n- **总进球数**: `2-3` 球 (期望值: `3.11`)\n\n---\n### 🏅 模型独立输出对照\n*   **Elo 概率**: 主胜 23% | 平 25% | 客 52%\n*   **xG 期望**: 主队 1.45 / 客队 1.66 (基础期望)\n*   **Dixon-Coles 修正**: τ 值为 -0.120 (平局相关性参数)\n*   **Monte Carlo 模拟**: 中位数比分 `1-1`，95% 置信区间主队 `[0-4]` / 客队 `[0-5]`\n\n---\n### 📊 盘口校准输入\n*   📉 **大小球校准**: 盘口 2.75, 大球公平概率 51.0%\n*   ⚖️ **让球校准**: 主队盘口 -0.50, 主队赢盘公平概率 49.5%\n\n---\n### 🏆 精准比分概率 TOP 5\n0. **`1-1`** --- 12.0% [█░░░░░░░░░]\n1. **`1-2`** --- 8.9% [█░░░░░░░░░]\n2. **`2-1`** --- 7.8% [█░░░░░░░░░]\n3. **`2-2`** --- 6.5% [█░░░░░░░░░]\n4. **`0-2`** --- 6.2% [█░░░░░░░░░]\n\n---\n### 🎲 进球数及双建概率\n- **0-1 球**: 17.1% [██░░░░░░░░]\n- **2-3 球**: 45.2% [█████░░░░░]\n- **4+ 球**: 37.7% [████░░░░░░]\n- **双方建功 (BTTS)**: 是 63.2% [██████░░░░] | 否 36.8% [████░░░░░░]\n\n---\n### 🛡️ 风险对冲与冷防建议\n- **冷门期望不败率** (主胜或平局 (挪威不败)): 54.9% [█████░░░░░]\n- **首选冷防比分**: `1-1` (胜率: 12.0%)\n- **三大赛果首选比分分布**: \n  *   🏠 主胜首选: `2-1` (7.8%)\n  *   🤝 平局首选: `1-1` (12.0%)\n  *   🚀 客胜首选: `1-2` (8.9%)\n- **市场投资期望值 (EV)**: `主胜: +6.2%, 平局: -7.7%, 客胜: -10.6%`\n- **最佳期望值推荐 (Value Bet)**: 偏向 `主胜` (EV值为 6.2%, 具备正向投注价值)\n\n---\n### 💰 智能资金分配与对冲投注单 (预算: 1000 元)\n### 🔴 策略 A: 等收益分投 (首筑基, 平滑波动)\n- 比分 `1-1` (估算 7.07) — 投 `290.8` 元 (中返 2056.0 元)\n- 比分 `1-2` (估算 9.52) — 投 `216.0` 元 (中返 2056.0 元)\n- 比分 `2-1` (估算 10.96) — 投 `187.6` 元 (中返 2056.0 元)\n- 比分 `2-2` (估算 13.17) — 投 `156.1` 元 (中返 2056.0 元)\n- 比分 `0-2` (估算 13.75) — 投 `149.5` 元 (中返 2056.0 元)\n👑 **策略 A 净期望利润**: `+1056.0` 元 (固定净回报率: `+105.6`%)\n### 🔵 策略 B: 保本主攻分投 (中后期爆发, 主攻暴利)\n- 💛 **保本对冲** `1-1` (估算 7.07) — 投 `141.4` 元 (中返 `1000` 元, 保本不赔)\n- 🚀 **主攻比分** `1-2` (估算 9.52) — 投 `261.5` 元 (中返 `2489.6` 元, 净赚 `+1489.6` 元)\n- 🚀 **主攻比分** `2-1` (估算 10.96) — 投 `227.1` 元 (中返 `2489.4` 元, 净赚 `+1489.4` 元)\n- 🚀 **主攻比分** `2-2` (估算 13.17) — 投 `189.0` 元 (中返 `2488.9` 元, 净赚 `+1488.9` 元)\n- 🚀 **主攻比分** `0-2` (估算 13.75) — 投 `180.9` 元 (中返 `2487.9` 元, 净赚 `+1487.9` 元)\n💪 **策略 B 综述**: 重仓主打胜局高回报, 一旦爆冷打出平局首选比分, 退还全部本金, 本场无风险。\n",
    "timestamp": "2026-07-11 10:57:32"
  },
  {
    "params": {
      "home_team": "挪威",
      "away_team": "英格兰",
      "home_odds": 3.55,
      "away_odds": 1.98
    },
    "report": "## 🎯 Match: 挪威 vs 英格兰\n---\n### 🎗️ 核心预测 (p_final 贝叶斯融合)\n- **主胜概率**: 29.9% [███░░░░░░░]\n- **平局概率**: 24.9% [██░░░░░░░░]\n- **客胜概率**: 45.2% [█████░░░░░]\n- **首选推荐**: `客胜`\n- **推荐比分**: `1-1` / `1-2`\n- **总进球数**: `2-3` 球 (期望值: `3.11`)\n\n---\n### 🏅 模型独立输出对照\n*   **Elo 概率**: 主胜 23% | 平 25% | 客 52%\n*   **xG 期望**: 主队 1.45 / 客队 1.66 (基础期望)\n*   **Dixon-Coles 修正**: τ 值为 -0.120 (平局相关性参数)\n*   **Monte Carlo 模拟**: 中位数比分 `1-1`，95% 置信区间主队 `[0-4]` / 客队 `[0-5]`\n\n---\n### 📊 盘口校准输入\n*   📉 **大小球校准**: 盘口 2.75, 大球公平概率 51.0%\n*   ⚖️ **让球校准**: 主队盘口 -0.50, 主队赢盘公平概率 49.5%\n\n---\n### 🏆 精准比分概率 TOP 5\n0. **`1-1`** --- 12.0% [█░░░░░░░░░]\n1. **`1-2`** --- 8.9% [█░░░░░░░░░]\n2. **`2-1`** --- 7.8% [█░░░░░░░░░]\n3. **`2-2`** --- 6.5% [█░░░░░░░░░]\n4. **`0-2`** --- 6.2% [█░░░░░░░░░]\n\n---\n### 🎲 进球数及双建概率\n- **0-1 球**: 17.1% [██░░░░░░░░]\n- **2-3 球**: 45.2% [█████░░░░░]\n- **4+ 球**: 37.7% [████░░░░░░]\n- **双方建功 (BTTS)**: 是 63.2% [██████░░░░] | 否 36.8% [████░░░░░░]\n\n---\n### 🛡️ 风险对冲与冷防建议\n- **冷门期望不败率** (主胜或平局 (挪威不败)): 54.8% [█████░░░░░]\n- **首选冷防比分**: `1-1` (胜率: 12.0%)\n- **三大赛果首选比分分布**: \n  *   🏠 主胜首选: `2-1` (7.8%)\n  *   🤝 平局首选: `1-1` (12.0%)\n  *   🚀 客胜首选: `1-2` (8.9%)\n- **市场投资期望值 (EV)**: `主胜: +6.2%, 平局: -7.9%, 客胜: -10.5%`\n- **最佳期望值推荐 (Value Bet)**: 偏向 `主胜` (EV值为 6.2%, 具备正向投注价值)\n\n---\n### 💰 智能资金分配与对冲投注单 (预算: 1000 元)\n### 🔴 策略 A: 等收益分投 (首筑基, 平滑波动)\n- 比分 `1-1` (估算 7.07) — 投 `290.8` 元 (中返 2056.0 元)\n- 比分 `1-2` (估算 9.52) — 投 `216.0` 元 (中返 2056.0 元)\n- 比分 `2-1` (估算 10.96) — 投 `187.6` 元 (中返 2056.0 元)\n- 比分 `2-2` (估算 13.17) — 投 `156.1` 元 (中返 2056.0 元)\n- 比分 `0-2` (估算 13.75) — 投 `149.5` 元 (中返 2056.0 元)\n👑 **策略 A 净期望利润**: `+1056.0` 元 (固定净回报率: `+105.6`%)\n### 🔵 策略 B: 保本主攻分投 (中后期爆发, 主攻暴利)\n- 💛 **保本对冲** `1-1` (估算 7.07) — 投 `141.4` 元 (中返 `1000` 元, 保本不赔)\n- 🚀 **主攻比分** `1-2` (估算 9.52) — 投 `261.5` 元 (中返 `2489.6` 元, 净赚 `+1489.6` 元)\n- 🚀 **主攻比分** `2-1` (估算 10.96) — 投 `227.1` 元 (中返 `2489.4` 元, 净赚 `+1489.4` 元)\n- 🚀 **主攻比分** `2-2` (估算 13.17) — 投 `189.0` 元 (中返 `2488.9` 元, 净赚 `+1488.9` 元)\n- 🚀 **主攻比分** `0-2` (估算 13.75) — 投 `180.9` 元 (中返 `2487.9` 元, 净赚 `+1487.9` 元)\n💪 **策略 B 综述**: 重仓主打胜局高回报, 一旦爆冷打出平局首选比分, 退还全部本金, 本场无风险。\n",
    "timestamp": "2026-07-11 10:56:31"
  },
  {
    "params": {
      "home_team": "法国",
      "away_team": "摩洛哥",
      "home_odds": 1.55,
      "away_odds": 5.8
    },
    "report": "## 🎯 Match: 法国 vs 摩洛哥\n---\n### 🎗️ 核心预测 (p_final 贝叶斯融合)\n- **主胜概率**: 65.0% [███████░░░]\n- **平局概率**: 22.7% [██░░░░░░░░]\n- **客胜概率**: 12.3% [█░░░░░░░░░]\n- **首选推荐**: `主胜`\n- **推荐比分**: `2-0` / `1-0`\n- **总进球数**: `2-3` 球 (期望值: `2.61`)\n\n---\n### 🏅 模型独立输出对照\n*   **Elo 概率**: 主胜 69% | 平 22% | 客 9%\n*   **xG 期望**: 主队 1.84 / 客队 0.77 (基础期望)\n*   **Dixon-Coles 修正**: τ 值为 -0.120 (平局相关性参数)\n*   **Monte Carlo 模拟**: 中位数比分 `2-0`，95% 置信区间主队 `[0-5]` / 客队 `[0-3]`\n\n---\n### 📊 盘口校准输入\n*   📉 **大小球校准**: 盘口 2.50, 大球公平概率 47.4%\n*   ⚖️ **让球校准**: 主队盘口 -1.00, 主队赢盘公平概率 48.5%\n\n---\n### 🏆 精准比分概率 TOP 5\n0. **`2-0`** --- 12.4% [█░░░░░░░░░]\n1. **`1-0`** --- 12.3% [█░░░░░░░░░]\n2. **`1-1`** --- 11.7% [█░░░░░░░░░]\n3. **`2-1`** --- 9.6% [█░░░░░░░░░]\n4. **`0-0`** --- 8.6% [█░░░░░░░░░]\n\n---\n### 🎲 进球数及双建概率\n- **0-1 球**: 25.3% [███░░░░░░░]\n- **2-3 球**: 48.1% [█████░░░░░]\n- **4+ 球**: 26.6% [███░░░░░░░]\n- **双方建功 (BTTS)**: 是 46.5% [█████░░░░░] | 否 53.5% [█████░░░░░]\n\n---\n### 🛡️ 风险对冲与冷防建议\n- **冷门期望不败率** (平局或客胜 (摩洛哥不败)): 35.0% [███░░░░░░░]\n- **首选冷防比分**: `1-1` (胜率: 11.7%)\n- **三大赛果首选比分分布**: \n  *   🏠 主胜首选: `2-0` (12.4%)\n  *   🤝 平局首选: `1-1` (11.7%)\n  *   🚀 客胜首选: `0-1` (4.4%)\n- **市场投资期望值 (EV)**: `主胜: +0.8%, 平局: -7.1%, 客胜: -28.5%`\n- **最佳期望值推荐 (Value Bet)**: 偏向 `主胜` (EV值为 0.8%, 具备正向投注价值)\n\n---\n### 💰 智能资金分配与对冲投注单 (预算: 1000 元)\n### 🔴 策略 A: 等收益分投 (首筑基, 平滑波动)\n- 比分 `2-0` (估算 6.85) — 投 `227.3` 元 (中返 1557.1 元)\n- 比分 `1-0` (估算 6.93) — 投 `224.7` 元 (中返 1557.1 元)\n- 比分 `1-1` (估算 7.26) — 投 `214.5` 元 (中返 1557.1 元)\n- 比分 `2-1` (估算 8.86) — 投 `175.7` 元 (中返 1557.1 元)\n- 比分 `0-0` (估算 9.87) — 投 `157.8` 元 (中返 1557.1 元)\n👑 **策略 A 净期望利润**: `+557.1` 元 (固定净回报率: `+55.7`%)\n### 🔵 策略 B: 保本主攻分投 (中后期爆发, 主攻暴利)\n- 💛 **保本对冲** `1-1` (估算 7.26) — 投 `137.7` 元 (中返 `1000` 元, 保本不赔)\n- 🚀 **主攻比分** `2-0` (估算 6.85) — 投 `249.5` 元 (中返 `1709.0` 元, 净赚 `+709.0` 元)\n- 🚀 **主攻比分** `1-0` (估算 6.93) — 投 `246.6` 元 (中返 `1708.6` 元, 净赚 `+708.6` 元)\n- 🚀 **主攻比分** `2-1` (估算 8.86) — 投 `193.0` 元 (中返 `1709.6` 元, 净赚 `+709.6` 元)\n- 🚀 **主攻比分** `0-0` (估算 9.87) — 投 `173.3` 元 (中返 `1710.1` 元, 净赚 `+710.1` 元)\n💪 **策略 B 综述**: 重仓主打胜局高回报, 一旦爆冷打出平局首选比分, 退还全部本金, 本场无风险。\n",
    "timestamp": "2026-07-11 09:35:30"
  }
]